badgebtle/__init__.py
badgebtle/badgebtle.py
badgebtle-0.1.4.dist-info/METADATA
badgebtle-0.1.4.dist-info/RECORD
badgebtle-0.1.4.dist-info/WHEEL
badgebtle-0.1.4.dist-info/top_level.txt
