Metadata-Version: 2.1
Name: badgebtle
Version: 0.1.4
Summary: DEF CON badge bluetooth library
Home-page: https://github.com/dczia/python-badgebtle
Author: Robert Bost
License: UNKNOWN
Platform: UNKNOWN
Classifier: Programming Language :: Python :: 3
Classifier: License :: OSI Approved :: MIT License
Classifier: Operating System :: OS Independent
Requires-Dist: bluepy
